gth_exporter/__init__.py
gth_exporter/bluez.py
gth_exporter/graphite.py
gth_exporter/main.py
gth_exporter/metric.py
gth_exporter/prometheus.py
gth_exporter-1.0.0.dist-info/entry_points.txt
gth_exporter-1.0.0.dist-info/LICENSE
gth_exporter-1.0.0.dist-info/WHEEL
gth_exporter-1.0.0.dist-info/METADATA
gth_exporter-1.0.0.dist-info/RECORD
