Metadata-Version: 2.3
Name: gth_exporter
Version: 1.0.0
Summary: GoveeLife Bluetooth Termomenter Hygromether Exporter
Author-email: Jürgen Hötzel <juergen@hoetzel.info>
Classifier: License :: OSI Approved :: MIT License
Requires-Dist: PyGObject >= 3.50.0 
Requires-Dist: pyright ; extra == "dev"
Requires-Dist: ruff ; extra == "dev"
Requires-Dist: PyGObject-stubs ; extra == "dev"
Project-URL: Home, https://github.com/juergenhoetzel/gth_exporter
Provides-Extra: dev
